LICENSE
MANIFEST.in
README.md
setup.py
apicultor/__init__.py
apicultor/run_mir_analysis.py
apicultor/constraints/__init__.py
apicultor/constraints/bounds.py
apicultor/constraints/dynamic_range.py
apicultor/constraints/tempo.py
apicultor/constraints/time_freq.py
apicultor/data/__init__.py
apicultor/doc/__init__.py
apicultor/emotion/MusicEmotionMachine.py
apicultor/emotion/__init__.py
apicultor/gradients/__init__.py
apicultor/gradients/ascent.py
apicultor/gradients/descent.py
apicultor/gradients/subproblem.py
apicultor/helper/ArchiveWebScrapingDownload.py
apicultor/helper/Build_csv.py
apicultor/helper/WebScrapingDownload.py
apicultor/helper/__init__.py
apicultor/helper/convert-to-wav.py
apicultor/helper/convert_to_ogg.py
apicultor/helper/download-test-data.sh
apicultor/helper/gen_config.py
apicultor/machine_learning/SoundSimilarity.py
apicultor/machine_learning/__init__.py
apicultor/machine_learning/cache.py
apicultor/machine_learning/cross_validation.py
apicultor/machine_learning/dependency.py
apicultor/machine_learning/explain.py
apicultor/machine_learning/fairness.py
apicultor/machine_learning/metrics.py
apicultor/machine_learning/quality.py
apicultor/machine_learning/visuals.py
apicultor/mir/MIRState.py
apicultor/mir/MirAnalysis.py
apicultor/mir/__init__.py
apicultor/mir/db/Fill_DB.py
apicultor/mir/db/FreesoundDB.py
apicultor/mir/db/JsonMirFilesData.py
apicultor/mir/db/RedPanalDB.py
apicultor/mir/db/__init__.py
apicultor/mir/db/api.py
apicultor/segmentation/DoSegmentation.py
apicultor/segmentation/FixedSegmentation.py
apicultor/segmentation/RandomSegmentation.py
apicultor/segmentation/__init__.py
apicultor/sonification/Sonification.py
apicultor/sonification/__init__.py
apicultor/state_machine/DemoSimpleStateMachine.py
apicultor/state_machine/PlayCtrlState.py
apicultor/state_machine/SMComposition.py
apicultor/state_machine/__init__.py
apicultor/state_machine/composition1.json
apicultor/state_machine/composition1_diagram.js
apicultor_dev.egg-info/PKG-INFO
apicultor_dev.egg-info/SOURCES.txt
apicultor_dev.egg-info/dependency_links.txt
apicultor_dev.egg-info/entry_points.txt
apicultor_dev.egg-info/requires.txt
apicultor_dev.egg-info/top_level.txt
