Metadata-Version: 2.1
Name: apicultor-dev
Version: 2.0.1
Summary: BigData system of sound effects, remixes and sound collections
Home-page: https://www.github.com/sonidosmutantes/apicultor
Author: Hernán Ordiales, Marcelo Tuller
Author-email: hordiales@gmail.com, marscrophimself@protonmail.com
License: GPLv3
Download-URL: https://github.com/sonidosmutantes/apicultor/archive/refs/heads/dev.zip
Keywords: deeplearning,ml,mlops,svm,music,dsp,sound,audio
Platform: UNKNOWN
Classifier: Development Status :: 6 - Mature
Classifier: Intended Audience :: Developers
Classifier: Topic :: Multimedia :: Sound/Audio :: Analysis
Classifier: Programming Language :: Python :: 3.9
License-File: LICENSE
